ollama_hydra/__init__.py
ollama_hydra/client.py
ollama_hydra/modelfile.py
ollama_hydra/proxy.py
ollama_hydra-0.1.8.dist-info/LICENSE
ollama_hydra-0.1.8.dist-info/METADATA
ollama_hydra-0.1.8.dist-info/WHEEL
ollama_hydra-0.1.8.dist-info/entry_points.txt
ollama_hydra-0.1.8.dist-info/top_level.txt
ollama_hydra-0.1.8.dist-info/RECORD
